TRuML-0.0.0.dist-info/METADATA
TRuML-0.0.0.dist-info/RECORD
TRuML-0.0.0.dist-info/WHEEL
TRuML-0.0.0.dist-info/entry_points.txt
TRuML-0.0.0.dist-info/top_level.txt
truml/__init__.py
truml/__main__.py
truml/objects.py
truml/parsers.py
truml/rbexceptions.py
truml/readers.py
truml/truml.py
truml/utils.py
