Metadata-Version: 2.1
Name: TRuML
Version: 0.0.0
Summary: Translation between BNGL models and Kappa models
Home-page: UNKNOWN
Author: Ryan Suderman
Author-email: ryants@lanl.gov
License: UNKNOWN
Platform: UNKNOWN
Requires-Dist: pyparsing
Requires-Dist: deepdiff
Requires-Dist: networkx
Requires-Dist: nose
